[
    {
        "id":"1",
        "url":"http://p9p0nd4a5.bkt.clouddn.com/1.mp3",
        "name":"大千世界",
        "descript":"大千世界-杨朗朗",
        "lyric":"[00:07.16]作词：杨朗朗\n[00:07.61]作曲：杨朗朗\n[00:09.38]人来人往 车来车往 杂乱无章\n[00:25.60]你来我往 礼尚来往 老死不相往\n[00:30.99]天下熙熙 天下攘攘 皆为利往\n[00:38.34]人为财死 鸟为食亡 无利不疯狂\n[00:45.99]商贾权贵 王侯将相 宁有种乎？\n[00:51.22]贩夫走卒 引车卖浆 黄粱梦一场！\n[00:56.79]人为刀俎 我为鱼肉 鸟尽弓藏\n[01:03.85]败寇成王 千秋功过 历史谁梳妆\n[01:10.72]口袋里剩下多少的希望\n[01:19.54]心底还残留多少的信仰\n[01:26.64]欲望像野草一样的疯长\n[01:34.93]生命如鲜花一样的无长\n[01:45.73]我还能怎样？\n[02:04.68]大千世界 无奇不有 包罗万象\n[02:08.30]芸芸众生 朗朗乾坤 大戏谁来唱\n[02:13.16]你的主张 我的思想 天地碰撞\n[02:21.19]黑白颠倒 无中生有 全凭嘴一张\n[02:28.80]鸡飞狗跳 鸡鸣狗盗 蝇营之辈\n[02:34.72]拔刀相助 救死扶伤 谁为你收场\n[02:39.94]一己之私 丧尽天良 报应不爽\n[02:46.67]一家之言 万马齐喑 正义谁伸张\n[02:55.44]谁的虔诚沾染了血光\n[03:02.88]谁的谎言被正义的歌唱\n[03:10.80]谁的大厦建立在虚无上\n[03:20.62]谁的善良被无情的流放\n[03:28.14]你又能怎样？\n"
        
    },
    {
        "id":"2",
        "url":"http://p9p0nd4a5.bkt.clouddn.com/2.mp3",
        "name":"伶仃",
        "descript":"伶仃-陈慧琳",
        "lyric":"[00:00.00] 作词 : 改编词:林夕\n[00:21.200]并没有想等的口讯 叫孤独\n[00:27.200]有节目 差点开心到哭\n[00:33.410]让我屈服 有甚么都觉得心足 只恐拒绝便折福\n[00:47.590]寂寞也许都只因我 太拣择\n[00:53.920]过路人 怎可能诱惑\n[01:00.250]满脑空白 怨地呼天也讲资格 想因某人哭湿过手帕\n[01:13.190]我问良心 为免孤独谁都合衬\n[01:20.920]偶尔更寂寞都不要紧\n[01:26.440]再别疑心 闭起这双眼才能亲一个吻\n[01:33.900]然后多么渴望原来某君 极深得我心\n[01:40.200]只怕难捱的是我 什么手也拖\n[01:48.990]将更难过 这点我最清楚\n[01:54.000]伶仃得我这一个 或这种好过做情侣\n[02:03.910]然后我自己却未爱过\n[02:27.360]瞒着良心 为免孤独谁都合衬\n[02:35.160]偶尔更寂寞都不要紧\n[02:40.590]无谓疑心 闭起这双眼才能亲一个吻\n[02:48.050]然后多么渴望原来某君 极深得我心\n[02:54.510]只怕难捱的是我 什么手也拖\n[03:03.260]将更难过 这点我最清楚\n[03:08.340]伶仃得我这一个 或这种好过做情侣\n[03:18.190]然后我自己却未爱过\n[03:24.680]然后大家互相对坐 都不敢对望\n[03:35.380]然后发现他也未爱过\n"
        
    },
    {
        "id":"3",
        "url":"http://p9p0nd4a5.bkt.clouddn.com/3.mp3",
        "name":"天后",
        "descript":"陈势安-天后-再爱一遍",
        "lyric":"[00:00.00] 作曲 : 彭学斌\n[00:01.00] 作词 : 彭学斌\n[00:23.170] 终于找到借口趁着醉意上心头\n[00:31.090] 表达我所有感受\n[00:34.629] 寂寞渐浓沉默留在舞池角落\n[00:41.279] 你说的太少或太多\n[00:44.579] 都会让人更惶恐\n[00:48.359] 谁任由谁放纵谁会先让出自由\n[00:55.390] 最后一定总是我\n[00:58.590] 双脚悬空在你冷酷热情间游走\n[01:05.049] 被侵占所有还要笑着接受\n[01:10.790] 我嫉妒你的爱气势如虹\n[01:16.279] 像个人气高居不下的天后\n[01:22.379] 你要的不是我而是一种虚荣\n[01:28.249] 有人疼才显得多么出众\n[01:34.339] 我陷入盲目狂恋的宽容\n[01:40.289] 成全了你万众宠爱的天后\n[01:46.229] 若爱只剩诱惑只剩彼此忍受\n[01:52.308] 别再互相折磨\n[01:57.239] 因为我们都有错\n[02:01.759]\n[02:14.940] 推开苍白的手推开苍白的厮守\n[02:22.000] 管你有多么失措\n[02:24.910] 别再叫我心软是最致命的脆弱\n[02:32.140] 我明明都懂却仍拼死效忠\n[02:38.100] 我嫉妒你的爱气势如虹\n[02:43.320] 像个人气高居不下的天后\n[02:49.300] 你要的不是我而是一种虚荣\n[02:55.290] 有人疼才显得多么出众\n[03:01.190] 我陷入盲目狂恋的宽容\n[03:07.280] 成全了你万众宠爱的天后\n[03:13.310] 若爱只剩诱惑只剩彼此忍受\n[03:19.300] 别再互相折磨\n[03:24.310] 因为我们都有错\n[03:29.070]\n[03:49.229] 如果有一天爱不再迷惑\n[03:55.280] 足够去看清所有是非对错\n[04:01.220] 直到那个时候你在我的心中\n[04:07.140] 将不再被歌颂把你当作天后\n[04:19.910] 不会再是我\n[04:24.100]\n"
        
    },
    {
        "id":"4",
        "url":"http://p9p0nd4a5.bkt.clouddn.com/4.mp3",
        "name":"夜色(粤语版)",
        "descript":"梁剑东-夜色",
        "lyric":"[00:00.00] 作曲 : 安英民\n[00:01.00] 作词 : 梁剑东\n[00:13.610]原唱：梁剑东\n[01:33.840]荧光的彩灯吊灯射灯继续照耀\n[01:37.530]频闪的激光今晚发挥继续揭晓\n[01:41.360]独立大屏幕 独立座一角\n[01:44.860]饮番两杯啤酒冻饮算不算是快乐\n[01:48.510]今天开心了吗\n[01:51.140]今天寂寞了吧\n[01:52.600]请抱起吉他\n[01:54.330]独自寻乐唱吧\n[01:56.280]还不足够吗\n[01:58.210]请抱紧我啦\n[01:59.960]来一起跳舞吧\n[02:02.750]开心跳动迷迷糊糊地便过去\n[02:06.130]多少快乐濛濛胧胧地在这里\n[02:09.840]其实你已经不需再追 继续舞吧\n[02:15.570]随着叫声Hi Hi Hi\n[02:18.510]la la la la la la la la la la lalalala\n[02:22.280]la la la la la la la la la la lalalala\n[02:26.190]la la la la la la la la la la lalalala\n[02:29.890]la la la la la la la la la la lalalala\n[02:34.670]\n[03:05.660]荧光的彩灯吊灯射灯继续照耀\n[03:09.380]频闪的激光今晚发挥继续揭晓\n[03:12.810]独立大屏幕 独立座一角\n[03:16.610]饮番两杯啤酒冻饮算不算是快乐\n[03:20.110]今天开心了吗\n[03:22.530]今天寂寞了吧\n[03:24.230]请抱起吉他\n[03:26.060]独自寻乐唱吧\n[03:28.210]还不足够吗\n[03:29.980]请抱紧我啦\n[03:31.810]来一起跳舞吧\n[03:34.380]开心跳动迷迷糊糊地便过去\n[03:37.990]多少快乐濛濛胧胧地在这里\n[03:41.730]其实你已经不需再追 继续舞吧\n[03:47.420]随着叫声Hi Hi Hi\n[03:49.670]开心跳动迷迷糊糊地便过去\n[03:53.010]多少快乐濛濛胧胧地在这里\n[03:56.620]其实你已经不需再追 继续舞吧\n[04:02.590]随着叫声Hi Hi Hi\n[04:05.340]la la la la la la la la la la lalalala\n[04:09.130]la la la la la la la la la la lalalala\n[04:12.970]la la la la la la la la la la lalalala\n[04:16.690]la la la la la la la la la la lalalala\n"
        
    },
    {
        "id":"5",
        "url":"http://p9p0nd4a5.bkt.clouddn.com/5.mp3",
        "name":"初梦",
        "descript":"大梦想家乐园-初梦",
        "lyric":"[00:00.00] 作曲 : 葛明航\n[00:01.00] 作词 : 葛明航\n[00:12.17]编曲：葛明航、葛金桥\n[00:15.89]仿佛画面近如眼睦\n[00:24.50]仿佛天边遍是彩虹\n[00:29.17]和星空\n[00:32.89]仿佛当阳光近了生活\n[00:36.70]静静等\n[00:38.71]你味道 围绕\n[00:42.37]空气中争强欲动\n[00:47.63]当美好都因你而倾倒\n[00:54.15]当一切都将向你微笑\n[01:00.76]当快乐的要求不重要\n[01:04.12]你可了解你之重要\n[01:08.34]我知道你的好 我知道\n[01:11.96]幸福之中相拥祈祷\n[01:40.07]仿佛画面近如眼睦\n[01:46.34]仿佛天边遍是彩虹\n[01:51.05]和星空\n[01:54.46]仿佛当阳光近了生活\n[01:58.87]静静等\n[02:00.93]你味道 围绕\n[02:04.35]空气中争强欲动\n[02:08.95]当美好都因你而倾倒\n[02:16.36]当一切都将向你微笑\n[02:23.15]当快乐的要求不重要\n[02:26.72]你可了解你之重要\n[02:30.33]我知道你的好 我知道\n[02:34.53]幸福之中相拥祈祷\n[02:43.30]吉他：葛明航\n[02:48.11]贝斯：郭锐\n[02:52.56]鼓：朱彬赫\n[02:57.86]制作人：葛明航\n[03:10.62]-------大梦想家乐团Dreamer-------\n"
        
    },
    {
        "id":"6",
        "url":"http://p9p0nd4a5.bkt.clouddn.com/6.mp3",
        "name":"安和桥",
        "descript":"宋冬野-安和桥北",
        "lyric":"[00:37.496]让我再看你一遍\n[00:38.694]从南到北\n[00:44.476]像是被五环路蒙住的双眼\n[00:52.659]请你再讲一遍\n[00:54.496]关于那天\n[00:58.496]抱着盒子的姑娘\n[01:03.300]和擦汗的男人\n[01:06.780]我知道 那些夏天\n[01:09.780]就像青春一样回不来\n[01:13.360]代替梦想的也只能是勉为其难\n[01:20.379]我知道 吹过的牛逼\n[01:24.180]也会随青春一笑了之\n[01:28.480]让我困在城市里\n[01:31.769]纪念你\n[01:36.370]让我再尝一口\n[01:39.500]秋天的酒\n[01:44.185]一直往南方开\n[01:46.117]不会太久\n[01:52.669]让我再听一遍\n[01:53.495]最美的那一句\n[01:58.400]你回家了\n[02:01.680]我在等你呢\n[02:35.299]我知道 那些夏天\n[02:38.752]就像青春一样回不来\n[02:43.075]代替梦想的也只能是勉为其难\n[02:50.949]我知道 吹过的牛逼\n[02:52.998]也会随青春一笑了之\n[02:59.299]让我困在城市里 纪念你\n[03:04.778]我知道 那些夏天\n[03:08.849]就像你一样回不来\n[03:12.187]我也不会再对谁满怀期待\n[03:19.798]我知道 这个世界\n[03:22.898]每天都有太多遗憾\n[03:27.357]所以你好 再见\n"
        
    },
    {
        "id":"7",
        "url":"http://p9p0nd4a5.bkt.clouddn.com/7.mp3",
        "name":"与你常在",
        "descript":"与你常在-eason and the duo band",
        "lyric":"[00:00.00] 作曲 : 汪苏泷\n[00:01.00] 作词 : 汪苏泷\n[00:05.70]编曲：吴烦\n[00:10.18]人海里\n[00:13.37]有千万种表情\n[00:16.16]我的每个情绪\n[00:18.94]怎样传递给你\n[00:19.93]你的姓名\n[00:24.75]像是微风轻轻\n[00:27.78]让我心跳不停\n[00:30.68]让我失去冷静\n[00:33.55]命运波折不停\n[00:36.98]冥冥中已注定\n[00:39.55]这感情\n[00:40.86]需要你\n[00:42.33]来定义\n[00:45.13]想和你在一起\n[00:48.07]永远地在一起\n[00:50.95]我对你的关心\n[00:53.77]超出朋友关系\n[00:56.64]想和你在一起\n[00:59.30]真实地在一起\n[01:02.35]我疯狂地彻底\n[01:05.05]你要奉陪到底\n[01:07.98]要定你\n[01:14.15]这夏季\n[01:16.10]转眼就要过去\n[01:18.88]我读过的诗句\n[01:21.95]多想 念给你听\n[01:25.00]命运波折不停\n[01:28.01]冥冥中已注定\n[01:30.86]这感情\n[01:32.39]需要你\n[01:33.87]来定义\n[01:36.64]想和你在一起\n[01:39.45]永远地在一起\n[01:42.28]我对你的关心\n[01:45.18]超出朋友关系\n[01:48.07]想和你在一起\n[01:50.76]真实地在一起\n[01:53.99]我疯狂地彻底\n[01:56.44]你要奉陪到底\n[01:59.40]我不怕有天会失去\n[02:05.61]当我闭上眼睛\n[02:08.33]你存在我呼吸\n[02:22.68]想和你在一起\n[02:25.13]永远地在一起\n[02:28.14]我对你的关心\n[02:30.95]超出朋友关系\n[02:33.80]想和你在一起\n[02:36.43]真实地在一起\n[02:39.15]我疯狂地彻底\n[02:42.20]你要奉陪到底\n[02:46.33]人海里\n[02:50.59]有千万种表情\n[02:53.72]我的每个情绪\n[02:56.58]怎样传递给你\n[02:59.50]制作人：任寒冰\n[03:00.95]吉他：吴烦\n[03:01.86]贝斯：吴烦\n[03:02.74]鼓：hayato\n[03:03.58]和音：梁古驰\n[03:04.10]录音：任寒冰@行人Studio\n[03:04.62]混音：章谋杰@行人Studio\n[03:05.25]母带：曹飞@行人Studio\n"
        
    },
    {     
        "id":"8",
        "url":"http://p9p0nd4a5.bkt.clouddn.com/8.mp3",
        "name":"Girl Like You",
        "descript":"Maroon 5 / Cardi B -Girls Like You",
        "lyric":"[00:07.400]Spent 24 hours\n[00:09.610]I need more hours with you\n[00:15.170]You spent the weekend\n[00:17.020]Gettin even ooo\n[00:22.830]We spent the late nights\n[00:24.730]Makin things right between us\n[00:30.420]Now it's all good baby\n[00:32.300]Roll that back wood baby\n[00:34.250]And play me close\n[00:38.680]Cause girls like you\n[00:40.180]Run round with guys like me\n[00:41.990]Til sundown when I come through\n[00:43.980]I need a girl like you\n[00:45.750]Yay yay\n[00:46.790]Girls like you\n[00:47.700]Love fun\n[00:48.350]And yeah me too\n[00:49.540]What I want\n[00:50.300]When I come through\n[00:51.480]I need a girl like you\n[00:53.410]Yay yay\n[00:55.470]Yay yay yay\n[00:57.240]Yay yay yay\n[00:59.400]I need a girl like you\n[01:01.190]Yay yay\n[01:03.090]Yay yay yay\n[01:05.010]Yay yay yay\n[01:07.020]I need a girl like you\n[01:09.070]I spent last night\n[01:11.030]On the last flight to you\n[01:16.820]Took a whole day up\n[01:18.570]Tryna get way up ooo\n[01:24.440]We spent the daylight\n[01:26.160]Tryna make things right between us\n[01:32.070]Now it's all good baby\n[01:33.790]Roll that back wood baby\n[01:35.760]And play me close (yeah)\n[01:40.190]Cause girls like you\n[01:41.500]Run round with guys like me\n[01:43.350]Til sundown when I come through\n[01:45.310]I need a girl like you\n[01:47.240]Yay yay\n[01:47.990]Girls like you\n[01:49.150]Love fun\n[01:49.870]And yeah me too\n[01:51.000]What I want\n[01:51.610]When I come through\n[01:52.980]I need a girl like you\n[01:54.860]Yay yay\n[01:56.860]Yay yay yay\n[01:58.670]Yay yay yay\n[02:00.720]I need a girl like you\n[02:02.490]Yay yay\n[02:04.430]Yay yay yay\n[02:06.490]Yay yay yay\n[02:08.400]I need a girl like you\n[02:10.210]Yay yay\n[02:16.380]I need a girl like you\n[02:17.860]Yay yay\n[02:23.930]I need a girl like you\n[02:26.740]Maybe it’s 6:45\n[02:28.480]Maybe I’m barely alive\n[02:30.470]Maybe you’ve taken my shit for the last time, yeah\n[02:34.400]Maybe I know that I’m drunk\n[02:36.200]Maybe I know you’re the one\n[02:38.070]Maybe I’m thinkin it’s better if you drive\n[02:43.680]Not too long ago I was dancin’ for dollars\n[02:45.660]Knew it was really real if I let you met my momma\n[02:47.350]You don’t want a girl like me I’m too crazy\n[02:49.240]But every other girl you meet is fugazy (oookkurrt)\n[02:51.480]I’m sure them other girls were nice enough\n[02:52.950]But you need someone to spice it up\n[02:55.270]So who you gonna call Cardi Cardi\n[02:57.020]To come and rev it up like a Harley Harley\n[02:58.960]Why is the best fruit always forbidden\n[03:00.720]I’m coming to you now doin’ 20 over the limit\n[03:02.720]The red light red light stop (stop)\n[03:04.590]I don’t play when it comes to my heart, lets get it though\n[03:06.670]I don’t really want a white horse and a carriage\n[03:08.830]I’m thinking more white porsches and karats\n[03:10.540]I need you right here cause every time you fall\n[03:12.580]I play with this kitty like you play witch your guitar\n[03:14.290]Cause girls like you (girls like you)\n[03:16.260]Run round with guys like me\n[03:17.510]Til sundown (sundown) when I come through\n[03:19.360]I need a girl like you (oohhh)\n[03:21.360]Yay yay\n[03:21.960]Girls like you\n[03:23.270]Love fun\n[03:23.890]And yeah me too\n[03:25.090]What I want\n[03:25.870]When I come through\n[03:27.080]I need a girl like you (like you)\n[03:28.890]Yay yay\n[03:30.850]Yay yay yay\n[03:33.000]Yay yay yay\n[03:34.920]I need a girl like you\n[03:36.660]Yay yay\n[03:38.920]Yay yay yay\n[03:40.700]Yay yay yay\n[03:42.680]I need a girl like you\n"
        
    },
    {
        "id":"9",
        "url":"http://p9p0nd4a5.bkt.clouddn.com/9.mp3",
        "name":"小苹果",
        "descript":"小苹果-回音哥",
        "lyric":"[00:00.00]回音哥 - 小苹果\n[00:16.405]我种下一颗种子\n[00:18.207]终于长出了果实\n[00:20.157]今天是个伟大日子\n[00:23.930]摘下星星送给你\n[00:25.880]拽下月亮送给你\n[00:27.736]让太阳每天为你升起\n[00:31.696]变成蜡烛燃烧自己\n[00:33.700]只为照亮你\n[00:35.615]把我一切都献给你\n[00:37.516]只要你欢喜\n[00:39.484]你让我每个明天都\n[00:41.389]变得有意义\n[00:43.127]生命虽短爱你永远\n[00:45.161]不离不弃\n[00:46.975]你是我的小呀小苹果儿\n[00:50.731]怎么爱你我都不嫌多\n[00:54.183]红红的小脸儿温暖我的心窝\n[00:58.558]点亮我生命的火 火火火火火\n[01:02.505]你是我的小呀小苹果儿\n[01:06.106]就像天边最美的云朵\n[01:09.610]春天又来到了花开满山坡\n[01:13.852]种下希望就会收获\n[01:33.174]从不觉得你讨厌\n[01:35.64]你的一切都喜欢\n[01:36.865]有你每天都很新鲜\n[01:40.732]有你阳光更灿烂\n[01:42.684]有你黑夜不黑暗\n[01:44.588]你是白云我是蓝天\n[01:48.501]春天和你漫步在盛开的 花丛间\n[01:52.475]夏天夜晚陪你一起看 星星眨眼\n[01:56.275]秋天黄昏与你徜徉在 金色麦田\n[01:59.990]冬天雪花飞舞有你 更加温暖\n[02:03.891]你是我的小呀小苹果儿\n[02:07.488]怎么爱你我都不嫌多\n[02:11.63]红红的小脸儿温暖我的心窝\n[02:15.303]点亮我生命的火 火火火火火\n[02:19.235]你是我的小呀小苹果儿\n[02:22.890]就像天边最美的云朵\n[02:26.343]春天又来到了花开满山坡\n[02:30.299]种下希望就会收获\n[02:50.57]你是我的小呀小苹果儿\n[02:53.896]怎么爱你我都不嫌多\n[02:57.187]红红的小脸儿温暖我的心窝\n[03:01.376]点亮我生命的火 火火火火火\n[03:05.297]你是我的小呀小苹果儿\n[03:08.998]就像天边最美的云朵\n[03:12.548]春天又来到了花开满山坡\n[03:16.402]种下希望就会收获\n"
        
    },
    {
        "id":"10",
        "url":"http://p9p0nd4a5.bkt.clouddn.com/10.mp3",
        "name":"Like That",
        "descript":"Like That-吴亦凡",
        "lyric":"[00:00.00] 作曲 : Kris Wu/Louis Bell\n[00:00.650] 作词 : Kris Wu/Louis Bell\n[00:01.950]Produced by FKi 1st/Trackbangas\n[00:03.130]\n[00:18.910]I’m about to throw away my money\n[00:21.430]On you\n[00:22.900]I’m about to throw it all up\n[00:26.060]Tell me what you want and we going\n[00:30.530]Its on you\n[00:31.650]Anything you want its all us\n[00:35.070]I ain’t never seen a Girl like that\n[00:37.270]Tell me if we take a chance like that\n[00:39.410]Got me spending all my cash like that\n[00:41.570]Keep on doing what I like\n[00:43.000]Like that\n[00:44.670]Girl like that\n[00:46.060]Tell me if we take a chance like that\n[00:48.260]Got me spending all my cash like that\n[00:50.310]Keep on doing what I like\n[00:51.180]Like that\n[00:53.520]She a 10 and yea she's bad\n[00:54.880]Yea I love my baby\n[00:58.320]I might spend a little bag\n[00:59.380]Just to keep you dipping\n[01:02.020]Anytime I'm in the city\n[01:03.500]You can be right with me\n[01:06.240]When I’m talking\n[01:07.680]I aint frontin\n[01:08.100]Thats the way we live it\n[01:10.540]She feeling me\n[01:11.790]I can tell by the way she stares she stares\n[01:15.210]I know what you’re thinking\n[01:16.450]It don’t really make no sense no sense\n[01:19.230]Who can resist\n[01:20.280]And I don’t wanna miss one time\n[01:24.140]Just me and you\n[01:27.950]Oh all the time\n[01:30.520]Oh you on my mind\n[01:32.620]Oh ya all the time\n[01:37.300]I’m about to throw away my money\n[01:40.350]On you\n[01:41.480]I’m about to throw it all up\n[01:45.930]Tell me what you want and we going\n[01:49.150]Its on you\n[01:50.210]Anything you want its all us\n[01:53.850]I ain’t never seen a\n[01:54.620]Girl like that\n[01:56.010]Tell me if we take a chance like that\n[01:58.030]Got me spending all my cash like that\n[02:00.140]Keep on doing what I like\n[02:01.750]Like that\n[02:02.920]Girl like that\n[02:04.680]Tell me if we take a chance like that\n[02:06.710]Got me spending all my cash like that\n[02:08.920]Keep on doing what I like\n[02:10.680]Like that\n[02:11.730]All night on the phone\n[02:13.790]24/7 We go\n[02:15.900]Come on baby give me some more putting on a show for sure\n[02:20.830]Feel so good inside\n[02:23.180]I know just yo style\n[02:25.410]Feel it start to rise\n[02:28.150]We can get it right though\n[02:29.750]I don’t know if you ride or die\n[02:31.450]I don’t know if you’re bout this life\n[02:33.590]I don’t know if you’re tryna play\n[02:36.070]Let me know if you’re tryna play\n[02:38.130]We can go\n[02:39.020]We can take new heights like this\n[02:40.610]We can get it on in the night like this\n[02:42.980]Turn me up like like a fire\n[02:44.670]Heat me up burn me up\n[02:46.350]Like a lighter\n[02:47.080]I’m about to throw away my money\n[02:50.570]On you\n[02:51.300]I’m about to throw it all up\n[02:55.650]Tell me what you want and we going\n[02:58.670]Its on you\n[03:00.000]Anything you want its all us\n[03:03.180]I ain’t never seen a\n[03:04.420]Girl like that\n[03:05.720]Tell me if we take a chance like that\n[03:07.780]Got me spending all my cash like that\n[03:10.060]Keep on doing what I like\n[03:11.470]Like that\n[03:12.680]Girl like that\n[03:14.410]Tell me if we take a chance like that\n[03:16.590]Got me spending all my cash like that\n[03:18.920]Keep on doing what I like\n[03:20.210]Like that\n[03:21.720]I don’t know if you ride or die\n[03:25.450]I don’t know if you’re bout this life\n[03:29.860]We can go\n[03:31.380]We can take new heights like this\n[03:33.220]We can get it on in the night like this\n[03:35.180]Turn me up like like a fire\n[03:36.990]Heat me up burn me up\n[03:38.550]Like a lighter\n"
        
    }
]
